mylibrary/ module1.py
mylibrary/ module2.py
mylibrary/__init__.py
mylibrary/subpackage/__init__.py
mylibrary/subpackage/submodule1.py
mylibrary/subpackage/submodule2.py
kaviproject-0.6.dist-info/LICENSE
kaviproject-0.6.dist-info/METADATA
kaviproject-0.6.dist-info/WHEEL
kaviproject-0.6.dist-info/top_level.txt
kaviproject-0.6.dist-info/RECORD
