Metadata-Version: 2.1
Name: kaviproject
Version: 0.6
Summary: A description of your library
Home-page: https://github.com/kaviarasan2720/my_library
Author: Kavi
Author-email: arasansk54@gmail.com
License: MIT
License-File: LICENSE
